termq/__init__.py
termq/chat_mode.py
termq/cli.py
termq/pdf_mode.py
termq/utils.py
termq/characters/c3po.json
termq/characters/c3po.txt
termq/characters/hal9000.json
termq/characters/hal9000.txt
termq-0.1.0.dist-info/licenses/LICENSE
termq-0.1.0.dist-info/METADATA
termq-0.1.0.dist-info/WHEEL
termq-0.1.0.dist-info/entry_points.txt
termq-0.1.0.dist-info/top_level.txt
termq-0.1.0.dist-info/RECORD
