Metadata-Version: 2.4
Name: termq
Version: 0.1.0
Summary: A minimal GPT chat client in the terminal
Author-email: Tommy <i@tjtl.io>
License: MIT
Project-URL: Homepage, https://github.com/yourusername/termq
Project-URL: Repository, https://github.com/yourusername/termq
Project-URL: Bug Tracker, https://github.com/yourusername/termq/issues
Keywords: openai,gpt,chat,terminal,cli
Classifier: Development Status :: 3 - Alpha
Classifier: Intended Audience :: Developers
Classifier: License :: OSI Approved :: MIT License
Classifier: Programming Language :: Python :: 3
Classifier: Programming Language :: Python :: 3.8
Classifier: Programming Language :: Python :: 3.9
Classifier: Programming Language :: Python :: 3.10
Classifier: Programming Language :: Python :: 3.11
Classifier: Programming Language :: Python :: 3.12
Requires-Python: >=3.8
License-File: LICENSE
Requires-Dist: openai==0.27.8
Requires-Dist: termcolor>=2.3.0
Requires-Dist: rich>=13.4.2
Requires-Dist: PyMuPDF>=1.22.3
Requires-Dist: ocrmypdf>=13.7.0
Requires-Dist: pyperclip==1.8.2
Provides-Extra: dev
Requires-Dist: pytest>=7.0; extra == "dev"
Requires-Dist: black>=22.0; extra == "dev"
Requires-Dist: flake8>=4.0; extra == "dev"
Dynamic: license-file
